dlpx/__init__.py
dlpx/virtualization/__init__.py
dlpx/virtualization/_internal/VERSION
dlpx/virtualization/_internal/__init__.py
dlpx/virtualization/_internal/__main__.py
dlpx/virtualization/_internal/cli.py
dlpx/virtualization/_internal/click_util.py
dlpx/virtualization/_internal/codegen.py
dlpx/virtualization/_internal/const.py
dlpx/virtualization/_internal/delphix_client.py
dlpx/virtualization/_internal/exceptions.py
dlpx/virtualization/_internal/file_util.py
dlpx/virtualization/_internal/logging_util.py
dlpx/virtualization/_internal/package_util.py
dlpx/virtualization/_internal/plugin_dependency_util.py
dlpx/virtualization/_internal/plugin_importer.py
dlpx/virtualization/_internal/plugin_util.py
dlpx/virtualization/_internal/plugin_validator.py
dlpx/virtualization/_internal/schema_validator.py
dlpx/virtualization/_internal/settings.cfg
dlpx/virtualization/_internal/codegen/codegen-config.json
dlpx/virtualization/_internal/codegen/swagger-codegen-cli-2.3.1.jar
dlpx/virtualization/_internal/codegen/templates/__init__model.mustache
dlpx/virtualization/_internal/codegen/templates/base_model_.mustache
dlpx/virtualization/_internal/codegen/templates/model.mustache
dlpx/virtualization/_internal/codegen/templates/util.mustache
dlpx/virtualization/_internal/commands/__init__.py
dlpx/virtualization/_internal/commands/build.py
dlpx/virtualization/_internal/commands/download_logs.py
dlpx/virtualization/_internal/commands/initialize.py
dlpx/virtualization/_internal/commands/upload.py
dlpx/virtualization/_internal/commands/plugin_template/direct_operations.py.template
dlpx/virtualization/_internal/commands/plugin_template/entry_point.py.template
dlpx/virtualization/_internal/commands/plugin_template/schema_template.json
dlpx/virtualization/_internal/commands/plugin_template/staged_operations.py.template
dlpx/virtualization/_internal/validation_schemas/plugin_config_schema.json
dlpx/virtualization/_internal/validation_schemas/plugin_importer.yaml
dvp_tools-5.0.1.dist-info/LICENSE
dvp_tools-5.0.1.dist-info/METADATA
dvp_tools-5.0.1.dist-info/WHEEL
dvp_tools-5.0.1.dist-info/entry_points.txt
dvp_tools-5.0.1.dist-info/top_level.txt
dvp_tools-5.0.1.dist-info/RECORD
